wes_palette/__init__.py
wes_palette/wes_palette.py
wes_palette-0.1.2.dist-info/LICENSE
wes_palette-0.1.2.dist-info/METADATA
wes_palette-0.1.2.dist-info/WHEEL
wes_palette-0.1.2.dist-info/top_level.txt
wes_palette-0.1.2.dist-info/RECORD
